safecomms/__init__.py
safecomms/client.py
safecomms-0.1.1.dist-info/licenses/LICENSE
safecomms-0.1.1.dist-info/METADATA
safecomms-0.1.1.dist-info/WHEEL
safecomms-0.1.1.dist-info/top_level.txt
safecomms-0.1.1.dist-info/RECORD
